{
  "initialDate": "መነሻ ቀን",
  "finalDate": "መጨረሻ ቀን",
  "from": "ከ",
  "to": "እስከ",
  "getPdf": "በ PDF ፋይል ያውርዱ",
  "getExcel": "በ Excel ፋይል ያውርዱ",
  "standardService": "ስታንዳርድ አገልግሎቶች",
  "noStandardService": "ስታንዳርድ አገልግሎቶች አልተገኘም",
  "additionalService": "ተጨማሪ አገልግሎቶች",
  "noAdditionalServie": "ተጨማሪ አገልግሎት አልተገኘም",
  "subService": "ንዑስ አገልግሎቶች",
  "num": "ተቁ.",
  "activity": "ተግባር",
  "date": "ቀን",
  "freq": "መጠን",
  "quality": "ጥራት",
  "startingTime": "የተጀመረበት ሰአት",
  "endingTime": "ያለቀበት ሰአት",
  "totalHour": "የወሰደው ሰአት",
  "doneBy": "የሰራው ሰራተኛ",
  "action": "ማስተካከያወች",
  "edit": "አስተካክል",
  "delete": "አጥፋ",
  "cancel": "ይቅር",
  "save": "መዝግብ",
  "no":"ተው",
  "yes":"አዎ",
  "dateError": "ቀን ያስፈልጋል",
  "freqError": "መጠን ያስፈልጋል",
  "qualityError":"ጥራት ያስፈልጋል",
  "invalidQualityError":"እባክዎ ቁጥርን ከ % ጋር ያስገቡ",
  "startingTimeError": "የተጀመረበት ሰአት ያስፈልጋል",
  "endingTimeError": "ያለቀበት ሰአት ያስፈልጋል",
  "editMessage": "በተሳካ ሁኔታ ተስተካክሏል",
  "deleteMessage": "በተሳካ ሁኔታ ጠፍቷል",
  "fileService":"ዋና አገልግሎት",
  "fileSubService":"ንዑስ አገልግሎት",
  "fileActivity":"የንዑስ አገልግሎት ዋና ዋና ተግባራት",
  "fileDate":"ስራዉ የተሰረበት ቀን",
  "fileActivityPlan":"የዋና ተግባር እቅድ(የBPR)",
  "fileActivityperformance":"የዋና ዋና ተግባራት የመጠን፣የጊዜና ጥራት አፈፃፀም",
  "fileActivityAverage":"የዋና ዋና ተግባራት ጥቅል አፈፃፀም ስሌት",
  "fileSubServicePerformance":"የጥቅል የንዑስ አገልግሎት እቅድ አፈፃፀም ስሌት (የጥቅል የንዑስ አገልግሎት የስታን ዳር አፈፃፀም)",
  "employeeName":"ተግባሩን ያከናወነዉ ባለሞያ ሰም",
  "signature":"ፊርማ",
  "adminName":"ያረጋገጠዉ የቅርብ ሃላፊ ሰም"


}
